astro_prospector-1.4.1.dist-info/licenses/AUTHORS.rst
astro_prospector-1.4.1.dist-info/licenses/LICENSE
prospect/__init__.py
prospect/_version.py
prospect/fitting/__init__.py
prospect/fitting/convergence.py
prospect/fitting/ensemble.py
prospect/fitting/fitting.py
prospect/fitting/minimizer.py
prospect/fitting/nested.py
prospect/io/__init__.py
prospect/io/read_results.py
prospect/io/write_results.py
prospect/likelihood/__init__.py
prospect/likelihood/kernels.py
prospect/likelihood/likelihood.py
prospect/likelihood/noise_model.py
prospect/models/__init__.py
prospect/models/hyperparam_transforms.py
prospect/models/hyperparameters.py
prospect/models/model_setup.py
prospect/models/parameters.py
prospect/models/priors.py
prospect/models/priors_beta.py
prospect/models/sedmodel.py
prospect/models/templates.py
prospect/models/transforms.py
prospect/models/prior_data/behroozi_19_sfrd.txt
prospect/models/prior_data/gallazzi_05_massmet.txt
prospect/models/prior_data/mc_from_mocks.txt
prospect/models/prior_data/pdf_of_z_l20.txt
prospect/models/prior_data/pdf_of_z_l20t18.txt
prospect/models/prior_data/wmap9_z_age.txt
prospect/plotting/__init__.py
prospect/plotting/corner.py
prospect/plotting/figuremaker.py
prospect/plotting/sed.py
prospect/plotting/sfh.py
prospect/plotting/utils.py
prospect/sources/__init__.py
prospect/sources/boneyard.py
prospect/sources/constants.py
prospect/sources/dust_basis.py
prospect/sources/elines.py
prospect/sources/galaxy_basis.py
prospect/sources/ssp_basis.py
prospect/sources/star_basis.py
prospect/utils/__init__.py
prospect/utils/obsutils.py
prospect/utils/plotting.py
prospect/utils/prospect_args.py
prospect/utils/smoothing.py
astro_prospector-1.4.1.dist-info/METADATA
astro_prospector-1.4.1.dist-info/WHEEL
astro_prospector-1.4.1.dist-info/top_level.txt
astro_prospector-1.4.1.dist-info/RECORD
