Metadata-Version: 2.4
Name: astro-prospector
Version: 1.4.1
Summary: Stellar Population Inference from Spectra and SEDs
Author-email: Ben Johnson <benjamin.johnson@cfa.harvard.edu>
License: MIT License
Project-URL: Homepage, https://prospect.readthedocs.io/en/latest/
Project-URL: Source, https://github.com/bd-j/prospector
Project-URL: Bug Tracker, https://github.com/bd-j/prospector/issues
Classifier: Development Status :: 5 - Production/Stable
Classifier: Intended Audience :: Science/Research
Classifier: Programming Language :: Python
Classifier: License :: OSI Approved :: MIT License
Classifier: Natural Language :: English
Classifier: Topic :: Scientific/Engineering :: Astronomy
Requires-Python: >=3.9
License-File: LICENSE
License-File: AUTHORS.rst
Requires-Dist: numpy
Requires-Dist: h5py
Provides-Extra: test
Requires-Dist: pytest; extra == "test"
Requires-Dist: pytest-xdist; extra == "test"
Dynamic: license-file
